LICENSE.txt
MANIFEST.in
README.rst
setup.py
clime/__init__.py
clime/__main__.py
clime/core.py
clime/now.py
clime/util.py
clime.egg-info/PKG-INFO
clime.egg-info/SOURCES.txt
clime.egg-info/dependency_links.txt
clime.egg-info/entry_points.txt
clime.egg-info/top_level.txt
docs/Makefile
docs/api.rst
docs/changes.rst
docs/conf.py
docs/index.rst
docs/_templates/layout.html
examples/calc.py
examples/cmd_suffix.py
examples/lineno.py
examples/pyramid.py
examples/repeat.py
examples/reverse.py
examples/test_varargs.py
examples/climebox/README.rst
examples/climebox/climebox
examples/climebox/climebox.py
examples/climebox/dirname
examples/climebox/false
examples/climebox/pwd
tests/test.py