Metadata-Version: 1.1
Name: clime
Version: 0.3.1
Summary: Convert functions into multi-command program breezily.
Home-page: http://clime.mosky.tw/
Author: Mosky
Author-email: mosky.tw@gmail.com
License: MIT
Platform: any
Classifier: Development Status :: 5 - Production/Stable
Classifier: Environment :: Console
Classifier: Intended Audience :: Developers
Classifier: License :: OSI Approved :: MIT License
Classifier: Operating System :: OS Independent
Classifier: Programming Language :: Python
Classifier: Topic :: Utilities
Classifier: Topic :: Software Development :: Libraries :: Python Modules
